netbox_load_balancing/__init__.py
netbox_load_balancing/apps.py
netbox_load_balancing/navigation.py
netbox_load_balancing/template_content.py
netbox_load_balancing/urls.py
netbox_load_balancing/version.py
netbox_load_balancing/api/__init__.py
netbox_load_balancing/api/serializers.py
netbox_load_balancing/api/urls.py
netbox_load_balancing/api/views.py
netbox_load_balancing/api/serializsers_/__init__.py
netbox_load_balancing/api/serializsers_/health_monitor.py
netbox_load_balancing/api/serializsers_/lbservice.py
netbox_load_balancing/api/serializsers_/listener.py
netbox_load_balancing/api/serializsers_/member.py
netbox_load_balancing/api/serializsers_/pool.py
netbox_load_balancing/api/serializsers_/vip_address.py
netbox_load_balancing/api/serializsers_/vip_pool.py
netbox_load_balancing/choices/__init__.py
netbox_load_balancing/choices/choices.py
netbox_load_balancing/constants/__init__.py
netbox_load_balancing/constants/constants.py
netbox_load_balancing/filtersets/__init__.py
netbox_load_balancing/filtersets/health_monitor.py
netbox_load_balancing/filtersets/lbservice.py
netbox_load_balancing/filtersets/listener.py
netbox_load_balancing/filtersets/member.py
netbox_load_balancing/filtersets/pool.py
netbox_load_balancing/filtersets/vip_address.py
netbox_load_balancing/filtersets/vip_pool.py
netbox_load_balancing/forms/__init__.py
netbox_load_balancing/forms/health_monitor.py
netbox_load_balancing/forms/lbservice.py
netbox_load_balancing/forms/listener.py
netbox_load_balancing/forms/member.py
netbox_load_balancing/forms/pool.py
netbox_load_balancing/forms/vip_address.py
netbox_load_balancing/forms/vip_pool.py
netbox_load_balancing/graphql/__init__.py
netbox_load_balancing/graphql/enums.py
netbox_load_balancing/graphql/schema.py
netbox_load_balancing/graphql/types.py
netbox_load_balancing/graphql/filters/__init__.py
netbox_load_balancing/graphql/filters/health_monitor.py
netbox_load_balancing/graphql/filters/lbservice.py
netbox_load_balancing/graphql/filters/listener.py
netbox_load_balancing-1.3.0.dist-info/licenses/LICENSE
netbox_load_balancing-1.3.0.dist-info/METADATA
netbox_load_balancing-1.3.0.dist-info/WHEEL
netbox_load_balancing-1.3.0.dist-info/top_level.txt
netbox_load_balancing-1.3.0.dist-info/RECORD
