Metadata-Version: 2.4
Name: netbox-load-balancing
Version: 1.3.0
Summary: NetBox Load Balancing is a NetBox plugin that models a Load Balancing service based on the OpenStack SLB modelling
Author-email: Andy Wilson <andy@shady.org>
Project-URL: Homepage, https://github.com/andy-shady-org/netbox-load-balancing
Project-URL: Documentation, https://github.com/andy-shady-org/netbox-load-balancing/blob/main/README.md
Project-URL: Repository, https://github.com/andy-shady-org/netbox-load-balancing
Project-URL: Issues, https://github.com/andy-shady-org/netbox-load-balancing/issues
Keywords: netbox,netbox-plugin,load-balancing
Classifier: Development Status :: 5 - Production/Stable
Requires-Python: >=3.10
License-File: LICENSE
Dynamic: license-file
